main.py
mseep_tako_mcp-0.1.1.dist-info/METADATA
mseep_tako_mcp-0.1.1.dist-info/WHEEL
mseep_tako_mcp-0.1.1.dist-info/entry_points.txt
mseep_tako_mcp-0.1.1.dist-info/top_level.txt
mseep_tako_mcp-0.1.1.dist-info/RECORD
