Metadata-Version: 2.4
Name: mseep-tako-mcp
Version: 0.1.1
Summary: Tako MCP Server
Author-email: mseep <support@skydeck.ai>
Requires-Python: >=3.12
Requires-Dist: mcp[cli]==1.12.3
Requires-Dist: tako-sdk>=0.1.34
